tdi_python_tools/__init__.py
tdi_python_tools/arguments.py
tdi_python_tools/csv_processing.py
tdi_python_tools/file_processing.py
tdi_python_tools/ux_ui.py
tdi_python_tools-1.2.2.dist-info/METADATA
tdi_python_tools-1.2.2.dist-info/WHEEL
tdi_python_tools-1.2.2.dist-info/RECORD
