Metadata-Version: 2.3
Name: tdi-python-tools
Version: 1.2.2
Summary: A collection of useful tools for file handling, user input and csv exporting.
Requires-Python: >=3.12
Requires-Dist: tabulate>=0.9.0
